sumopy/__init__.py
sumopy/handler.py
sumopy-0.2.dist-info/LICENSE
sumopy-0.2.dist-info/METADATA
sumopy-0.2.dist-info/WHEEL
sumopy-0.2.dist-info/top_level.txt
sumopy-0.2.dist-info/RECORD
